consult7/__init__.py
consult7/__main__.py
consult7/constants.py
consult7/consultation.py
consult7/file_processor.py
consult7/server.py
consult7/token_utils.py
consult7/tool_definitions.py
consult7/providers/__init__.py
consult7/providers/base.py
consult7/providers/openrouter.py
consult7-3.2.0.dist-info/METADATA
consult7-3.2.0.dist-info/WHEEL
consult7-3.2.0.dist-info/entry_points.txt
consult7-3.2.0.dist-info/licenses/LICENSE
consult7-3.2.0.dist-info/RECORD
