Metadata-Version: 2.4
Name: consult7
Version: 3.2.0
Summary: MCP server for consulting large context window models to analyze extensive file collections via OpenRouter
Project-URL: Homepage, https://github.com/szeider/consult7
Project-URL: Repository, https://github.com/szeider/consult7
Project-URL: Issues, https://github.com/szeider/consult7/issues
Author-email: Stefan Szeider <stefan@szeider.net>
License: MIT
License-File: LICENSE
Keywords: code-analysis,large-context,llm,mcp,openrouter
Requires-Python: >=3.11
Requires-Dist: httpx>=0.28.1
Requires-Dist: mcp>=1.9.4
